/*     */ package com.nirvana.xml;@ScalaSignature(bytes = "\006\001\005UdaB\001\003!\003\r\t!\003\002\n16d7i\0348gS\036T!a\001\003\002\007alGN\003\002\006\r\0059a.\033:wC:\f'\"A\004\002\007\r|Wn\001\001\024\t\001Q\001C\006\t\003\0279i\021\001\004\006\002\033\005)1oY1mC&\021q\002\004\002\007\003:L(+\0324\021\005E!R\"\001\n\013\005M!\021\001B2pe\026L!!\006\n\003\025%s\027\016^5bY&TX\r\005\002\03095\t\001D\003\002\0325\005)1\017\03445U*\t1$\001\005he&T(\020\\3e\023\ti\002DA\004M_\036<\027N\\4\t\013}\001A\021\001\021\002\r\021Jg.\033;%)\005\t\003CA\006#\023\t\031CB\001\003V]&$\bbB\023\001\005\004%\tAJ\001\013G>tg-[4QCRDW#A\024\021\005!jS\"A\025\013\005)Z\023\001\0027b]\036T\021\001L\001\005U\0064\030-\003\002/S\t11\013\036:j]\036Da\001\r\001!\002\0239\023aC2p]\032Lw\rU1uQ\002BqA\r\001C\002\023\0051'\001\004nIVj\025\r]\013\002iA!QG\017\037=\033\0051$BA\0349\003\035iW\017^1cY\026T!!\017\007\002\025\r|G\016\\3di&|g.\003\002<m\t\031Q*\0319\021\005u\002eBA\006?\023\tyD\"\001\004Qe\026$WMZ\005\003]\005S!a\020\007\t\r\r\003\001\025!\0035\003\035iG-N'ba\002Bq!\022\001C\002\033\005a)\001\003gS2,W#\001\037\t\013!\003A\021A%\002\0171|\027\r\032-nYR\031!\nU)\021\007UZU*\003\002Mm\tQA*[:u\005V4g-\032:\021\005Eq\025BA(\023\005\035i\025\r\035\"fC:DQ!R$A\002qBQAU$A\002q\nq!\0327f[\026tG\017C\003U\001\021\005Q+\001\fhKR\024UO\0324fe\026$\027J\0349viN#(/Z1n+\0051\006CA,[\033\005A&BA-,\003\tIw.\003\002\\1\n\031\")\0364gKJ,G-\0238qkR\034FO]3b[\")A\013\001C\001;R\021aK\030\005\006\013r\003\r\001\020\005\006A\002!\t!Y\001\016gR\024Hk\\!se\006L\030J\034;\025\007\tD'\016E\002\fG\026L!\001\032\007\003\013\005\023(/Y=\021\005-1\027BA4\r\005\rIe\016\036\005\006S~\003\r\001P\001\004gR\024\bbB6`!\003\005\r\001P\001\ng\026\004\030M]1u_JDQ!\034\001\005\0029\fqb\035;s)>4uN]7bi2K7\017\036\013\003_z\0042\001\035=|\035\t\thO\004\002sk6\t1O\003\002u\021\0051AH]8pizJ\021!D\005\003o2\tq\001]1dW\006<W-\003\002zu\n!A*[:u\025\t9H\002\005\003\fy\026,\027BA?\r\005\031!V\017\0357fe!)\021\016\034a\001y!9\021\021\001\001\005\002\005\r\021!D:ueR{w)\033<f\023R,W\016\006\003\002\006\005M\001\003\0029y\003\017\001B!!\003\002\0205\021\0211\002\006\004\003\033!\021\001\0022fC:LA!!\005\002\f\tAq)\033<f\023R,W\016C\003j\002\007A\bC\004\002\030\001!\t!!\007\002\031\rD\027M\\4f)>d\025n\035;\025\007=\fY\002\003\004j\003+\001\r\001\020\005\b\003?\001A\021AA\021\003\031aw.\0313feV!\0211EA\025)\031\t)#a\017\002@A!\021qEA\025\031\001!\001\"a\013\002\036\t\007\021Q\006\002\002)F!\021qFA\033!\rY\021\021G\005\004\003ga!a\002(pi\"Lgn\032\t\004\027\005]\022bAA\035\031\t\031\021I\\=\t\017\005u\022Q\004a\001y\005I1\r\\1tg:\013W.\032\005\b\003\033\ti\0021\001N\021\035\t\031\005\001C\001\003\013\n1\"\0318z)>\034FO]5oOR\031A(a\022\t\021\005%\023\021\ta\001\003k\t\021A\036\005\b\003\033\002A\021AA(\003Q\021W/\0337e\003R$(O\022:p[6\013\007OQ3b]R!\021\021KA,!\021\tI!a\025\n\t\005U\0231\002\002\t\005\006\034X-\021;ue\"9\021\021LA&\001\004i\025!A7\t\023\005u\003!%A\005\002\005}\023aF:ueR{\027I\035:bs&sG\017\n3fM\006,H\016\036\0233+\t\t\tGK\002=\003GZ#!!\032\021\t\005\035\024\021O\007\003\003SRA!a\033\002n\005IQO\\2iK\016\\W\r\032\006\004\003_b\021AC1o]>$\030\r^5p]&!\0211OA5\005E)hn\0315fG.,GMV1sS\006t7-\032")
/*     */ public interface XmlConfig extends Initialize, Logging { void com$nirvana$xml$XmlConfig$_setter_$configPath_$eq(String paramString);
/*     */   void com$nirvana$xml$XmlConfig$_setter_$md5Map_$eq(Map paramMap);
/*     */   String configPath();
/*     */   Map<String, String> md5Map();
/*     */   String file();
/*     */   
/*     */   ListBuffer<MapBean> loadXml(String paramString1, String paramString2);
/*     */   
/*     */   BufferedInputStream getBufferedInputStream();
/*     */   
/*     */   BufferedInputStream getBufferedInputStream(String paramString);
/*     */   
/*     */   int[] strToArrayInt(String paramString1, String paramString2);
/*     */   
/*     */   String strToArrayInt$default$2();
/*     */   
/*     */   List<Tuple2<Object, Object>> strToFormatList(String paramString);
/*     */   
/*     */   List<GiveItem> strToGiveItem(String paramString);
/*     */   
/*     */   List<Tuple2<Object, Object>> changeToList(String paramString);
/*     */   
/*     */   <T> T loader(String paramString, MapBean paramMapBean);
/*     */   
/*     */   String anyToString(Object paramObject);
/*     */   
/*     */   BaseAttr buildAttrFromMapBean(MapBean paramMapBean);
/*     */   
/*     */   public final class XmlConfig$$anonfun$loadXml$1 extends AbstractFunction0<String> implements Serializable { public static final long serialVersionUID = 0L;
/*     */     
/*     */     public final String apply() {
/*  33 */       return (new StringBuilder()).append("open err:").append(this.file$1).toString();
/*     */     }
/*     */     private final String file$1;
/*     */     public XmlConfig$$anonfun$loadXml$1(XmlConfig $outer, String file$1) {} }
/*     */   public final class XmlConfig$$anonfun$loadXml$2 extends AbstractFunction1<Node, ListBuffer<MapBean>> implements Serializable { public static final long serialVersionUID = 0L;
/*     */     private final ObjectRef list$1;
/*     */     
/*     */     public XmlConfig$$anonfun$loadXml$2(XmlConfig $outer, ObjectRef list$1) {}
/*     */     
/*     */     public final ListBuffer<MapBean> apply(Node e) {
/*  43 */       MapBean m = MapBean$.MODULE$.empty();
/*  44 */       e.attributes().asAttrMap().foreach((Function1)new XmlConfig$$anonfun$loadXml$2$$anonfun$apply$1(this, m));
/*     */ 
/*     */ 
/*     */ 
/*     */ 
/*     */ 
/*     */ 
/*     */ 
/*     */ 
/*     */ 
/*     */ 
/*     */       
/*  56 */       return ((ListBuffer)this.list$1.elem).$plus$eq(m); } public final class XmlConfig$$anonfun$loadXml$2$$anonfun$apply$1 extends AbstractFunction1<Tuple2<String, String>, MapBean> implements Serializable {
/*     */       public static final long serialVersionUID = 0L; private final MapBean m$1; public XmlConfig$$anonfun$loadXml$2$$anonfun$apply$1(XmlConfig$$anonfun$loadXml$2 $outer, MapBean m$1) {} public final MapBean apply(Tuple2 p) { if (Tool$.MODULE$.isIntStr((String)p._2())) { try {  }
/*     */           catch (NumberFormatException numberFormatException) {} }
/*     */         else {  }
/*     */          Object value = Tool$.MODULE$.isDoubleStr((String)p._2()) ? BoxesRunTime.boxToDouble((new StringOps(Predef$.MODULE$.augmentString((String)p._2()))).toDouble()) : p._2(); return (MapBean)this.m$1.$plus$eq(Predef$ArrowAssoc$.MODULE$.$minus$greater$extension(Predef$.MODULE$.ArrowAssoc(p._1()), value)); } } } public final class XmlConfig$$anonfun$loadXml$3 extends AbstractFunction0<String> implements Serializable { public static final long serialVersionUID = 0L; private final String file$1;
/*  61 */     public final String apply() { return (new StringBuilder()).append("open err:").append(this.file$1).toString(); }
/*     */ 
/*     */ 
/*     */ 
/*     */     
/*     */     public XmlConfig$$anonfun$loadXml$3(XmlConfig $outer, String file$1) {} }
/*     */ 
/*     */ 
/*     */ 
/*     */   
/*     */   public final class XmlConfig$$anonfun$strToFormatList$1
/*     */     extends AbstractFunction1<String, Tuple2<Object, Object>>
/*     */     implements Serializable
/*     */   {
/*     */     public static final long serialVersionUID = 0L;
/*     */ 
/*     */ 
/*     */     
/*     */     public XmlConfig$$anonfun$strToFormatList$1(XmlConfig $outer) {}
/*     */ 
/*     */     
/*     */     public final Tuple2<Object, Object> apply(String s) {
/*  83 */       String[] ary = StringUtils.split(s, "_");
/*  84 */       return (Tuple2<Object, Object>)new Tuple2.mcII.sp((new StringOps(Predef$.MODULE$.augmentString(ary[0]))).toInt(), (new StringOps(Predef$.MODULE$.augmentString(ary[1]))).toInt());
/*     */     } }
/*     */   
/*     */   public final class XmlConfig$$anonfun$strToGiveItem$1 extends AbstractFunction1<String, GiveItem> implements Serializable {
/*     */     public static final long serialVersionUID = 0L;
/*     */     
/*     */     public XmlConfig$$anonfun$strToGiveItem$1(XmlConfig $outer) {}
/*     */     
/*     */     public final GiveItem apply(String s) {
/*  93 */       String[] ary = StringUtils.split(s, "_");
/*  94 */       if (Predef$.MODULE$.refArrayOps((Object[])ary).size() >= 3) {  } else {  }
/*  95 */        return new GiveItem((new StringOps(Predef$.MODULE$.augmentString(ary[0]))).toInt(), (new StringOps(Predef$.MODULE$.augmentString(ary[1]))).toInt(), GiveItem$.MODULE$.$lessinit$greater$default$3());
/*     */     }
/*     */   }
/*     */   
/*     */   public final class XmlConfig$$anonfun$changeToList$1
/*     */     extends AbstractFunction1<String, String[]> implements Serializable
/*     */   {
/*     */     public static final long serialVersionUID = 0L;
/*     */     
/* 104 */     public final String[] apply(String x$1) { return StringUtils.split(x$1, "_"); } public XmlConfig$$anonfun$changeToList$1(XmlConfig $outer) {} } public final class XmlConfig$$anonfun$changeToList$2 extends AbstractFunction1<String[], Tuple2<Object, Object>> implements Serializable { public static final long serialVersionUID = 0L; public final Tuple2<Object, Object> apply(String[] a) { return (Tuple2<Object, Object>)new Tuple2.mcII.sp((new StringOps(Predef$.MODULE$.augmentString(a[0]))).toInt(), (new StringOps(Predef$.MODULE$.augmentString(a[1]))).toInt()); }
/*     */ 
/*     */     
/*     */     public XmlConfig$$anonfun$changeToList$2(XmlConfig $outer) {} }
/*     */ 
/*     */   
/*     */   public final class XmlConfig$$anonfun$loader$1 extends AbstractFunction1<Field, BoxedUnit> implements Serializable {
/*     */     public static final long serialVersionUID = 0L;
/*     */     private final Object obj$1;
/*     */     private final MapBean bean$1;
/*     */     
/*     */     public XmlConfig$$anonfun$loader$1(XmlConfig $outer, Object obj$1, MapBean bean$1) {}
/*     */     
/*     */     public final void apply(Field p) {
/*     */       // Byte code:
/*     */       //   0: aload_1
/*     */       //   1: invokevirtual getName : ()Ljava/lang/String;
/*     */       //   4: astore_2
/*     */       //   5: aload_0
/*     */       //   6: getfield bean$1 : Lcom/nirvana/core/MapBean;
/*     */       //   9: aload_2
/*     */       //   10: invokevirtual contains : (Ljava/lang/Object;)Z
/*     */       //   13: ifeq -> 279
/*     */       //   16: aload_1
/*     */       //   17: invokevirtual getGenericType : ()Ljava/lang/reflect/Type;
/*     */       //   20: invokeinterface getTypeName : ()Ljava/lang/String;
/*     */       //   25: astore_3
/*     */       //   26: ldc 'int'
/*     */       //   28: aload_3
/*     */       //   29: invokevirtual equals : (Ljava/lang/Object;)Z
/*     */       //   32: ifeq -> 67
/*     */       //   35: aload_1
/*     */       //   36: iconst_1
/*     */       //   37: invokevirtual setAccessible : (Z)V
/*     */       //   40: aload_1
/*     */       //   41: aload_0
/*     */       //   42: getfield obj$1 : Ljava/lang/Object;
/*     */       //   45: aload_0
/*     */       //   46: getfield bean$1 : Lcom/nirvana/core/MapBean;
/*     */       //   49: aload_2
/*     */       //   50: invokevirtual getInt : (Ljava/lang/String;)I
/*     */       //   53: invokestatic boxToInteger : (I)Ljava/lang/Integer;
/*     */       //   56: invokevirtual set : (Ljava/lang/Object;Ljava/lang/Object;)V
/*     */       //   59: getstatic scala/runtime/BoxedUnit.UNIT : Lscala/runtime/BoxedUnit;
/*     */       //   62: astore #4
/*     */       //   64: goto -> 279
/*     */       //   67: ldc 'long'
/*     */       //   69: aload_3
/*     */       //   70: invokevirtual equals : (Ljava/lang/Object;)Z
/*     */       //   73: ifeq -> 108
/*     */       //   76: aload_1
/*     */       //   77: iconst_1
/*     */       //   78: invokevirtual setAccessible : (Z)V
/*     */       //   81: aload_1
/*     */       //   82: aload_0
/*     */       //   83: getfield obj$1 : Ljava/lang/Object;
/*     */       //   86: aload_0
/*     */       //   87: getfield bean$1 : Lcom/nirvana/core/MapBean;
/*     */       //   90: aload_2
/*     */       //   91: invokevirtual getLong : (Ljava/lang/String;)J
/*     */       //   94: invokestatic boxToLong : (J)Ljava/lang/Long;
/*     */       //   97: invokevirtual set : (Ljava/lang/Object;Ljava/lang/Object;)V
/*     */       //   100: getstatic scala/runtime/BoxedUnit.UNIT : Lscala/runtime/BoxedUnit;
/*     */       //   103: astore #4
/*     */       //   105: goto -> 279
/*     */       //   108: ldc 'double'
/*     */       //   110: aload_3
/*     */       //   111: invokevirtual equals : (Ljava/lang/Object;)Z
/*     */       //   114: ifeq -> 149
/*     */       //   117: aload_1
/*     */       //   118: iconst_1
/*     */       //   119: invokevirtual setAccessible : (Z)V
/*     */       //   122: aload_1
/*     */       //   123: aload_0
/*     */       //   124: getfield obj$1 : Ljava/lang/Object;
/*     */       //   127: aload_0
/*     */       //   128: getfield bean$1 : Lcom/nirvana/core/MapBean;
/*     */       //   131: aload_2
/*     */       //   132: invokevirtual getDouble : (Ljava/lang/String;)D
/*     */       //   135: invokestatic boxToDouble : (D)Ljava/lang/Double;
/*     */       //   138: invokevirtual set : (Ljava/lang/Object;Ljava/lang/Object;)V
/*     */       //   141: getstatic scala/runtime/BoxedUnit.UNIT : Lscala/runtime/BoxedUnit;
/*     */       //   144: astore #4
/*     */       //   146: goto -> 279
/*     */       //   149: ldc 'java.lang.String'
/*     */       //   151: aload_3
/*     */       //   152: invokevirtual equals : (Ljava/lang/Object;)Z
/*     */       //   155: ifeq -> 196
/*     */       //   158: aload_1
/*     */       //   159: iconst_1
/*     */       //   160: invokevirtual setAccessible : (Z)V
/*     */       //   163: aload_1
/*     */       //   164: aload_0
/*     */       //   165: getfield obj$1 : Ljava/lang/Object;
/*     */       //   168: aload_0
/*     */       //   169: getfield $outer : Lcom/nirvana/xml/XmlConfig;
/*     */       //   172: aload_0
/*     */       //   173: getfield bean$1 : Lcom/nirvana/core/MapBean;
/*     */       //   176: aload_2
/*     */       //   177: invokevirtual apply : (Ljava/lang/Object;)Ljava/lang/Object;
/*     */       //   180: invokeinterface anyToString : (Ljava/lang/Object;)Ljava/lang/String;
/*     */       //   185: invokevirtual set : (Ljava/lang/Object;Ljava/lang/Object;)V
/*     */       //   188: getstatic scala/runtime/BoxedUnit.UNIT : Lscala/runtime/BoxedUnit;
/*     */       //   191: astore #4
/*     */       //   193: goto -> 279
/*     */       //   196: ldc 'boolean'
/*     */       //   198: aload_3
/*     */       //   199: invokevirtual equals : (Ljava/lang/Object;)Z
/*     */       //   202: ifeq -> 270
/*     */       //   205: aload_1
/*     */       //   206: iconst_1
/*     */       //   207: invokevirtual setAccessible : (Z)V
/*     */       //   210: aload_1
/*     */       //   211: aload_0
/*     */       //   212: getfield obj$1 : Ljava/lang/Object;
/*     */       //   215: aload_0
/*     */       //   216: getfield bean$1 : Lcom/nirvana/core/MapBean;
/*     */       //   219: aload_2
/*     */       //   220: invokevirtual getString : (Ljava/lang/String;)Ljava/lang/String;
/*     */       //   223: invokestatic lowerCase : (Ljava/lang/String;)Ljava/lang/String;
/*     */       //   226: ldc 'true'
/*     */       //   228: astore #5
/*     */       //   230: dup
/*     */       //   231: ifnonnull -> 243
/*     */       //   234: pop
/*     */       //   235: aload #5
/*     */       //   237: ifnull -> 251
/*     */       //   240: goto -> 255
/*     */       //   243: aload #5
/*     */       //   245: invokevirtual equals : (Ljava/lang/Object;)Z
/*     */       //   248: ifeq -> 255
/*     */       //   251: iconst_1
/*     */       //   252: goto -> 256
/*     */       //   255: iconst_0
/*     */       //   256: invokestatic boxToBoolean : (Z)Ljava/lang/Boolean;
/*     */       //   259: invokevirtual set : (Ljava/lang/Object;Ljava/lang/Object;)V
/*     */       //   262: getstatic scala/runtime/BoxedUnit.UNIT : Lscala/runtime/BoxedUnit;
/*     */       //   265: astore #4
/*     */       //   267: goto -> 279
/*     */       //   270: new scala/MatchError
/*     */       //   273: dup
/*     */       //   274: aload_3
/*     */       //   275: invokespecial <init> : (Ljava/lang/Object;)V
/*     */       //   278: athrow
/*     */       //   279: return
/*     */       // Line number table:
/*     */       //   Java source line number -> byte code offset
/*     */       //   #112	-> 0
/*     */       //   #113	-> 5
/*     */       //   #114	-> 16
/*     */       //   #115	-> 26
/*     */       //   #116	-> 35
/*     */       //   #117	-> 40
/*     */       //   #115	-> 62
/*     */       //   #118	-> 67
/*     */       //   #119	-> 76
/*     */       //   #120	-> 81
/*     */       //   #118	-> 103
/*     */       //   #121	-> 108
/*     */       //   #122	-> 117
/*     */       //   #123	-> 122
/*     */       //   #121	-> 144
/*     */       //   #124	-> 149
/*     */       //   #125	-> 158
/*     */       //   #126	-> 163
/*     */       //   #124	-> 191
/*     */       //   #127	-> 196
/*     */       //   #128	-> 205
/*     */       //   #129	-> 210
/*     */       //   #127	-> 265
/*     */       //   #114	-> 270
/*     */       //   #111	-> 279
/*     */       // Local variable table:
/*     */       //   start	length	slot	name	descriptor
/*     */       //   0	280	0	this	Lcom/nirvana/xml/XmlConfig$$anonfun$loader$1;
/*     */       //   0	280	1	p	Ljava/lang/reflect/Field;
/*     */       //   5	275	2	name	Ljava/lang/String;
/*     */     }
/*     */   } }


/* Location:              D:\MTJ\mtj_master_jar\mtj_master.jar!\com\nirvana\xml\XmlConfig.class
 * Java compiler version: 6 (50.0)
 * JD-Core Version:       1.1.3
 */