/*    */ package com.nirvana.web;
/*    */ 
/*    */ import grizzled.slf4j.Logging;
/*    */ import org.eclipse.jetty.io.EofException;
/*    */ import scala.Function0;
/*    */ import scala.Serializable;
/*    */ import scala.runtime.AbstractFunction0;
/*    */ 
/*    */ @ScalaSignature(bytes = "\006\001!4A!\001\002\001\023\tyQ\t_2faRLwN\034$jYR,'O\003\002\004\t\005\031q/\0322\013\005\0251\021a\0028jeZ\fg.\031\006\002\017\005\0311m\\7\004\001M!\001A\003\n\033!\tY\001#D\001\r\025\tia\"\001\003mC:<'\"A\b\002\t)\fg/Y\005\003#1\021aa\0242kK\016$\bCA\n\031\033\005!\"BA\013\027\003\035\031XM\035<mKRT\021aF\001\006U\0064\030\r_\005\0033Q\021aAR5mi\026\024\bCA\016!\033\005a\"BA\017\037\003\025\031HN\032\033k\025\005y\022\001C4sSjTH.\0323\n\005\005b\"a\002'pO\036Lgn\032\005\006G\001!\t\001J\001\007y%t\027\016\036 \025\003\025\002\"A\n\001\016\003\tAQ\001\013\001\005\002%\nq\001Z3tiJ|\027\020F\001+!\tYc&D\001-\025\005i\023!B:dC2\f\027BA\030-\005\021)f.\033;\t\013E\002A\021\001\032\002\021\021|g)\0337uKJ$BAK\0329{!)A\007\ra\001k\005\031!/Z9\021\005M1\024BA\034\025\0059\031VM\035<mKR\024V-];fgRDQ!\017\031A\002i\n1A]3t!\t\0312(\003\002=)\ty1+\032:wY\026$(+Z:q_:\034X\rC\003?a\001\007q(A\003dQ\006Lg\016\005\002\024\001&\021\021\t\006\002\f\r&dG/\032:DQ\006Lg\016C\003D\001\021\005A)\001\003j]&$HC\001\026F\021\0251%\t1\001H\003\031\031wN\0344jOB\0211\003S\005\003\023R\021ABR5mi\026\0248i\0348gS\036DQa\023\001\005\n1\0131C]3ta>t7/Z*feZ,'/\022:s_J$BAK'V5\")aJ\023a\001\037\0069!/Z9vKN$\bC\001)T\033\005\t&B\001*\025\003\021AG\017\0369\n\005Q\013&A\005%uiB\034VM\035<mKR\024V-];fgRDQA\026&A\002]\013\001B]3ta>t7/\032\t\003!bK!!W)\003'!#H\017]*feZdW\r\036*fgB|gn]3\t\013mS\005\031\001/\002\003\025\004\"!X3\017\005y\033gBA0c\033\005\001'BA1\t\003\031a$o\\8u}%\tQ&\003\002eY\0059\001/Y2lC\036,\027B\0014h\005%!\006N]8xC\ndWM\003\002eY\001")
/*    */ public class ExceptionFilter implements Filter, Logging {
/*    */   private final Logger grizzled$slf4j$Logging$$_logger;
/*    */   
/* 13 */   private Logger grizzled$slf4j$Logging$$_logger$lzycompute() { synchronized (this) { if (!this.bitmap$0) { this.grizzled$slf4j$Logging$$_logger = Logging.class.grizzled$slf4j$Logging$$_logger(this); this.bitmap$0 = true; }  return this.grizzled$slf4j$Logging$$_logger; }  } private volatile boolean bitmap$0; public Logger grizzled$slf4j$Logging$$_logger() { return this.bitmap$0 ? this.grizzled$slf4j$Logging$$_logger : grizzled$slf4j$Logging$$_logger$lzycompute(); } public Logger logger() { return Logging.class.logger(this); } public String loggerName() { return Logging.class.loggerName(this); } public boolean isTraceEnabled() { return Logging.class.isTraceEnabled(this); } public void trace(Function0 msg) { Logging.class.trace(this, msg); } public void trace(Function0 msg, Function0 t) { Logging.class.trace(this, msg, t); } public boolean isDebugEnabled() { return Logging.class.isDebugEnabled(this); } public void debug(Function0 msg) { Logging.class.debug(this, msg); } public void debug(Function0 msg, Function0 t) { Logging.class.debug(this, msg, t); } public boolean isErrorEnabled() { return Logging.class.isErrorEnabled(this); } public void error(Function0 msg) { Logging.class.error(this, msg); } public void error(Function0 msg, Function0 t) { Logging.class.error(this, msg, t); } public boolean isInfoEnabled() { return Logging.class.isInfoEnabled(this); } public void info(Function0 msg) { Logging.class.info(this, msg); } public void info(Function0 msg, Function0 t) { Logging.class.info(this, msg, t); } public boolean isWarnEnabled() { return Logging.class.isWarnEnabled(this); } public void warn(Function0 msg) { Logging.class.warn(this, msg); } public void warn(Function0 msg, Function0 t) { Logging.class.warn(this, msg, t); } public ExceptionFilter() { Logging.class.$init$(this); }
/*    */   
/*    */   public void destroy() {}
/*    */   public void doFilter(ServletRequest req, ServletResponse res, FilterChain chain) {
/*    */     // Byte code:
/*    */     //   0: aload_1
/*    */     //   1: checkcast javax/servlet/http/HttpServletRequest
/*    */     //   4: astore #4
/*    */     //   6: aload_2
/*    */     //   7: checkcast javax/servlet/http/HttpServletResponse
/*    */     //   10: astore #5
/*    */     //   12: aload_3
/*    */     //   13: aload_1
/*    */     //   14: aload_2
/*    */     //   15: invokeinterface doFilter : (Ljavax/servlet/ServletRequest;Ljavax/servlet/ServletResponse;)V
/*    */     //   20: goto -> 393
/*    */     //   23: astore #6
/*    */     //   25: aload #6
/*    */     //   27: invokestatic create : (Ljava/lang/Object;)Lscala/runtime/ObjectRef;
/*    */     //   30: astore #10
/*    */     //   32: aload #10
/*    */     //   34: getfield elem : Ljava/lang/Object;
/*    */     //   37: checkcast java/lang/Throwable
/*    */     //   40: invokevirtual getClass : ()Ljava/lang/Class;
/*    */     //   43: ldc org/springframework/web/util/NestedServletException
/*    */     //   45: astore #11
/*    */     //   47: dup
/*    */     //   48: ifnonnull -> 60
/*    */     //   51: pop
/*    */     //   52: aload #11
/*    */     //   54: ifnull -> 68
/*    */     //   57: goto -> 122
/*    */     //   60: aload #11
/*    */     //   62: invokevirtual equals : (Ljava/lang/Object;)Z
/*    */     //   65: ifeq -> 122
/*    */     //   68: aload #10
/*    */     //   70: aload #6
/*    */     //   72: invokevirtual getCause : ()Ljava/lang/Throwable;
/*    */     //   75: putfield elem : Ljava/lang/Object;
/*    */     //   78: aload #10
/*    */     //   80: getfield elem : Ljava/lang/Object;
/*    */     //   83: checkcast java/lang/Throwable
/*    */     //   86: ifnonnull -> 122
/*    */     //   89: aload_0
/*    */     //   90: aload #4
/*    */     //   92: aload #5
/*    */     //   94: aload #6
/*    */     //   96: invokespecial responseServerError : (Ljavax/servlet/http/HttpServletRequest;Ljavax/servlet/http/HttpServletResponse;Ljava/lang/Throwable;)V
/*    */     //   99: aload_0
/*    */     //   100: new com/nirvana/web/ExceptionFilter$$anonfun$doFilter$5
/*    */     //   103: dup
/*    */     //   104: aload_0
/*    */     //   105: invokespecial <init> : (Lcom/nirvana/web/ExceptionFilter;)V
/*    */     //   108: new com/nirvana/web/ExceptionFilter$$anonfun$doFilter$6
/*    */     //   111: dup
/*    */     //   112: aload_0
/*    */     //   113: aload #6
/*    */     //   115: invokespecial <init> : (Lcom/nirvana/web/ExceptionFilter;Ljava/lang/Throwable;)V
/*    */     //   118: invokevirtual error : (Lscala/Function0;Lscala/Function0;)V
/*    */     //   121: return
/*    */     //   122: aload #10
/*    */     //   124: getfield elem : Ljava/lang/Object;
/*    */     //   127: checkcast java/lang/Throwable
/*    */     //   130: instanceof com/nirvana/exception/BusinessException
/*    */     //   133: ifeq -> 238
/*    */     //   136: aload_0
/*    */     //   137: invokevirtual logger : ()Lgrizzled/slf4j/Logger;
/*    */     //   140: invokevirtual isInfoEnabled : ()Z
/*    */     //   143: ifeq -> 182
/*    */     //   146: aload #10
/*    */     //   148: getfield elem : Ljava/lang/Object;
/*    */     //   151: checkcast java/lang/Throwable
/*    */     //   154: instanceof com/nirvana/exception/ForbiddenException
/*    */     //   157: ifeq -> 182
/*    */     //   160: aload_0
/*    */     //   161: new com/nirvana/web/ExceptionFilter$$anonfun$doFilter$7
/*    */     //   164: dup
/*    */     //   165: aload_0
/*    */     //   166: invokespecial <init> : (Lcom/nirvana/web/ExceptionFilter;)V
/*    */     //   169: new com/nirvana/web/ExceptionFilter$$anonfun$doFilter$8
/*    */     //   172: dup
/*    */     //   173: aload_0
/*    */     //   174: aload #10
/*    */     //   176: invokespecial <init> : (Lcom/nirvana/web/ExceptionFilter;Lscala/runtime/ObjectRef;)V
/*    */     //   179: invokevirtual info : (Lscala/Function0;Lscala/Function0;)V
/*    */     //   182: getstatic com/nirvana/web/ResponseUtil$.MODULE$ : Lcom/nirvana/web/ResponseUtil$;
/*    */     //   185: aload #5
/*    */     //   187: getstatic com/nirvana/core/MapBean$.MODULE$ : Lcom/nirvana/core/MapBean$;
/*    */     //   190: getstatic scala/Predef$.MODULE$ : Lscala/Predef$;
/*    */     //   193: iconst_1
/*    */     //   194: anewarray scala/Tuple2
/*    */     //   197: dup
/*    */     //   198: iconst_0
/*    */     //   199: getstatic scala/Predef$ArrowAssoc$.MODULE$ : Lscala/Predef$ArrowAssoc$;
/*    */     //   202: getstatic scala/Predef$.MODULE$ : Lscala/Predef$;
/*    */     //   205: ldc 'err'
/*    */     //   207: invokevirtual ArrowAssoc : (Ljava/lang/Object;)Ljava/lang/Object;
/*    */     //   210: aload #10
/*    */     //   212: getfield elem : Ljava/lang/Object;
/*    */     //   215: checkcast java/lang/Throwable
/*    */     //   218: invokevirtual getMessage : ()Ljava/lang/String;
/*    */     //   221: invokevirtual $minus$greater$extension : (Ljava/lang/Object;Ljava/lang/Object;)Lscala/Tuple2;
/*    */     //   224: aastore
/*    */     //   225: checkcast [Ljava/lang/Object;
/*    */     //   228: invokevirtual wrapRefArray : ([Ljava/lang/Object;)Lscala/collection/mutable/WrappedArray;
/*    */     //   231: invokevirtual apply : (Lscala/collection/Seq;)Lcom/nirvana/core/MapBean;
/*    */     //   234: invokevirtual responseJson : (Ljavax/servlet/http/HttpServletResponse;Lcom/nirvana/core/MapBean;)V
/*    */     //   237: return
/*    */     //   238: aload #10
/*    */     //   240: getfield elem : Ljava/lang/Object;
/*    */     //   243: checkcast java/lang/Throwable
/*    */     //   246: instanceof org/eclipse/jetty/io/EofException
/*    */     //   249: ifne -> 393
/*    */     //   252: aload_0
/*    */     //   253: aload #4
/*    */     //   255: aload #5
/*    */     //   257: aload #10
/*    */     //   259: getfield elem : Ljava/lang/Object;
/*    */     //   262: checkcast java/lang/Throwable
/*    */     //   265: invokespecial responseServerError : (Ljavax/servlet/http/HttpServletRequest;Ljavax/servlet/http/HttpServletResponse;Ljava/lang/Throwable;)V
/*    */     //   268: aload_0
/*    */     //   269: new com/nirvana/web/ExceptionFilter$$anonfun$doFilter$9
/*    */     //   272: dup
/*    */     //   273: aload_0
/*    */     //   274: invokespecial <init> : (Lcom/nirvana/web/ExceptionFilter;)V
/*    */     //   277: new com/nirvana/web/ExceptionFilter$$anonfun$doFilter$10
/*    */     //   280: dup
/*    */     //   281: aload_0
/*    */     //   282: aload #10
/*    */     //   284: invokespecial <init> : (Lcom/nirvana/web/ExceptionFilter;Lscala/runtime/ObjectRef;)V
/*    */     //   287: invokevirtual warn : (Lscala/Function0;Lscala/Function0;)V
/*    */     //   290: return
/*    */     //   291: astore #7
/*    */     //   293: aload_0
/*    */     //   294: new com/nirvana/web/ExceptionFilter$$anonfun$doFilter$3
/*    */     //   297: dup
/*    */     //   298: aload_0
/*    */     //   299: invokespecial <init> : (Lcom/nirvana/web/ExceptionFilter;)V
/*    */     //   302: new com/nirvana/web/ExceptionFilter$$anonfun$doFilter$4
/*    */     //   305: dup
/*    */     //   306: aload_0
/*    */     //   307: aload #7
/*    */     //   309: invokespecial <init> : (Lcom/nirvana/web/ExceptionFilter;Lorg/eclipse/jetty/io/EofException;)V
/*    */     //   312: invokevirtual debug : (Lscala/Function0;Lscala/Function0;)V
/*    */     //   315: goto -> 393
/*    */     //   318: astore #8
/*    */     //   320: getstatic com/nirvana/web/ResponseUtil$.MODULE$ : Lcom/nirvana/web/ResponseUtil$;
/*    */     //   323: aload #5
/*    */     //   325: getstatic com/nirvana/core/MapBean$.MODULE$ : Lcom/nirvana/core/MapBean$;
/*    */     //   328: getstatic scala/Predef$.MODULE$ : Lscala/Predef$;
/*    */     //   331: iconst_1
/*    */     //   332: anewarray scala/Tuple2
/*    */     //   335: dup
/*    */     //   336: iconst_0
/*    */     //   337: getstatic scala/Predef$ArrowAssoc$.MODULE$ : Lscala/Predef$ArrowAssoc$;
/*    */     //   340: getstatic scala/Predef$.MODULE$ : Lscala/Predef$;
/*    */     //   343: ldc 'err'
/*    */     //   345: invokevirtual ArrowAssoc : (Ljava/lang/Object;)Ljava/lang/Object;
/*    */     //   348: ldc '文件超过限制'
/*    */     //   350: invokevirtual $minus$greater$extension : (Ljava/lang/Object;Ljava/lang/Object;)Lscala/Tuple2;
/*    */     //   353: aastore
/*    */     //   354: checkcast [Ljava/lang/Object;
/*    */     //   357: invokevirtual wrapRefArray : ([Ljava/lang/Object;)Lscala/collection/mutable/WrappedArray;
/*    */     //   360: invokevirtual apply : (Lscala/collection/Seq;)Lcom/nirvana/core/MapBean;
/*    */     //   363: invokevirtual responseJson : (Ljavax/servlet/http/HttpServletResponse;Lcom/nirvana/core/MapBean;)V
/*    */     //   366: return
/*    */     //   367: astore #9
/*    */     //   369: aload_0
/*    */     //   370: new com/nirvana/web/ExceptionFilter$$anonfun$doFilter$1
/*    */     //   373: dup
/*    */     //   374: aload_0
/*    */     //   375: aload #4
/*    */     //   377: invokespecial <init> : (Lcom/nirvana/web/ExceptionFilter;Ljavax/servlet/http/HttpServletRequest;)V
/*    */     //   380: new com/nirvana/web/ExceptionFilter$$anonfun$doFilter$2
/*    */     //   383: dup
/*    */     //   384: aload_0
/*    */     //   385: aload #9
/*    */     //   387: invokespecial <init> : (Lcom/nirvana/web/ExceptionFilter;Ljava/lang/IllegalArgumentException;)V
/*    */     //   390: invokevirtual error : (Lscala/Function0;Lscala/Function0;)V
/*    */     //   393: return
/*    */     // Line number table:
/*    */     //   Java source line number -> byte code offset
/*    */     //   #18	-> 0
/*    */     //   #19	-> 6
/*    */     //   #21	-> 12
/*    */     //   #29	-> 23
/*    */     //   #20	-> 23
/*    */     //   #30	-> 25
/*    */     //   #31	-> 32
/*    */     //   #32	-> 68
/*    */     //   #33	-> 78
/*    */     //   #34	-> 89
/*    */     //   #35	-> 99
/*    */     //   #36	-> 121
/*    */     //   #39	-> 122
/*    */     //   #40	-> 136
/*    */     //   #41	-> 160
/*    */     //   #43	-> 182
/*    */     //   #44	-> 237
/*    */     //   #45	-> 238
/*    */     //   #48	-> 252
/*    */     //   #49	-> 268
/*    */     //   #50	-> 290
/*    */     //   #28	-> 291
/*    */     //   #20	-> 291
/*    */     //   #24	-> 318
/*    */     //   #20	-> 318
/*    */     //   #25	-> 320
/*    */     //   #26	-> 366
/*    */     //   #23	-> 367
/*    */     //   #20	-> 367
/*    */     //   #17	-> 393
/*    */     // Local variable table:
/*    */     //   start	length	slot	name	descriptor
/*    */     //   0	394	0	this	Lcom/nirvana/web/ExceptionFilter;
/*    */     //   0	394	1	req	Ljavax/servlet/ServletRequest;
/*    */     //   0	394	2	res	Ljavax/servlet/ServletResponse;
/*    */     //   0	394	3	chain	Ljavax/servlet/FilterChain;
/*    */     //   6	388	4	request	Ljavax/servlet/http/HttpServletRequest;
/*    */     //   12	382	5	response	Ljavax/servlet/http/HttpServletResponse;
/*    */     //   32	362	10	cause	Lscala/runtime/ObjectRef;
/*    */     // Exception table:
/*    */     //   from	to	target	type
/*    */     //   12	23	367	java/lang/IllegalArgumentException
/*    */     //   12	23	318	org/springframework/web/multipart/MaxUploadSizeExceededException
/*    */     //   12	23	291	org/eclipse/jetty/io/EofException
/*    */     //   12	23	23	finally
/*    */   }
/*    */   
/*    */   public final class ExceptionFilter$$anonfun$doFilter$1 extends AbstractFunction0<String> implements Serializable { public static final long serialVersionUID = 0L;
/*    */     private final HttpServletRequest request$1;
/*    */     
/* 23 */     public final String apply() { return this.request$1.getRequestURI(); } public ExceptionFilter$$anonfun$doFilter$1(ExceptionFilter $outer, HttpServletRequest request$1) {} } public final class ExceptionFilter$$anonfun$doFilter$2 extends AbstractFunction0<IllegalArgumentException> implements Serializable { public static final long serialVersionUID = 0L; private final IllegalArgumentException e$1; public final IllegalArgumentException apply() { return this.e$1; }
/*    */     
/*    */     public ExceptionFilter$$anonfun$doFilter$2(ExceptionFilter $outer, IllegalArgumentException e$1) {} }
/*    */   public final class ExceptionFilter$$anonfun$doFilter$3 extends AbstractFunction0<String> implements Serializable { public static final long serialVersionUID = 0L;
/*    */     
/* 28 */     public final String apply() { return ""; } public ExceptionFilter$$anonfun$doFilter$3(ExceptionFilter $outer) {} } public final class ExceptionFilter$$anonfun$doFilter$4 extends AbstractFunction0<EofException> implements Serializable { public static final long serialVersionUID = 0L; private final EofException e$2; public final EofException apply() { return this.e$2; }
/*    */ 
/*    */     
/*    */     public ExceptionFilter$$anonfun$doFilter$4(ExceptionFilter $outer, EofException e$2) {} }
/*    */   
/*    */   public final class ExceptionFilter$$anonfun$doFilter$5 extends AbstractFunction0<String> implements Serializable { public static final long serialVersionUID = 0L;
/*    */     
/* 35 */     public final String apply() { return ""; } public ExceptionFilter$$anonfun$doFilter$5(ExceptionFilter $outer) {} } public final class ExceptionFilter$$anonfun$doFilter$6 extends AbstractFunction0<Throwable> implements Serializable { public static final long serialVersionUID = 0L; private final Throwable e$3; public final Throwable apply() { return this.e$3; }
/*    */     
/*    */     public ExceptionFilter$$anonfun$doFilter$6(ExceptionFilter $outer, Throwable e$3) {} }
/*    */   
/*    */   public final class ExceptionFilter$$anonfun$doFilter$7 extends AbstractFunction0<String> implements Serializable { public static final long serialVersionUID = 0L;
/*    */     
/* 41 */     public final String apply() { return ""; } public ExceptionFilter$$anonfun$doFilter$7(ExceptionFilter $outer) {} } public final class ExceptionFilter$$anonfun$doFilter$8 extends AbstractFunction0<Throwable> implements Serializable { public static final long serialVersionUID = 0L; private final ObjectRef cause$1; public final Throwable apply() { return (Throwable)this.cause$1.elem; }
/*    */ 
/*    */     
/*    */     public ExceptionFilter$$anonfun$doFilter$8(ExceptionFilter $outer, ObjectRef cause$1) {} }
/*    */ 
/*    */   
/*    */   public final class ExceptionFilter$$anonfun$doFilter$9 extends AbstractFunction0<String> implements Serializable { public static final long serialVersionUID = 0L;
/*    */     
/* 49 */     public final String apply() { return ""; } public ExceptionFilter$$anonfun$doFilter$9(ExceptionFilter $outer) {} } public final class ExceptionFilter$$anonfun$doFilter$10 extends AbstractFunction0<Throwable> implements Serializable { public static final long serialVersionUID = 0L; private final ObjectRef cause$1; public final Throwable apply() { return (Throwable)this.cause$1.elem; }
/*    */ 
/*    */ 
/*    */ 
/*    */     
/*    */     public ExceptionFilter$$anonfun$doFilter$10(ExceptionFilter $outer, ObjectRef cause$1) {} }
/*    */ 
/*    */ 
/*    */ 
/*    */   
/*    */   public void init(FilterConfig config) {}
/*    */ 
/*    */   
/*    */   private void responseServerError(HttpServletRequest request, HttpServletResponse response, Throwable e) {
/* 63 */     (new scala.Tuple2[1])[0] = Predef$ArrowAssoc$.MODULE$.$minus$greater$extension(Predef$.MODULE$.ArrowAssoc("err"), "服务器出错"); ResponseUtil$.MODULE$.responseJson(response, MapBean$.MODULE$.apply((Seq)Predef$.MODULE$.wrapRefArray((Object[])new scala.Tuple2[1])));
/*    */   }
/*    */ }


/* Location:              D:\MTJ\mtj_master_jar\mtj_master.jar!\com\nirvana\web\ExceptionFilter.class
 * Java compiler version: 6 (50.0)
 * JD-Core Version:       1.1.3
 */