/*     */ package com.nirvana.bean;
/*     */ 
/*     */ import com.nirvana.core.MapBean;
/*     */ import java.util.Date;
/*     */ import scala.Predef$;
/*     */ import scala.Predef$ArrowAssoc$;
/*     */ 
/*     */ @ScalaSignature(bytes = "\006\001\t%h\001B\001\003\001%\021\021bU3sm\026\024H)\0324\013\005\r!\021\001\0022fC:T!!\002\004\002\0179L'O^1oC*\tq!A\002d_6\034\001a\005\002\001\025A\0211BD\007\002\031)\tQ\"A\003tG\006d\027-\003\002\020\031\t1\021I\\=SK\032DQ!\005\001\005\002I\ta\001P5oSRtD#A\n\021\005Q\001Q\"\001\002\t\023Y\001\001\031!a\001\n\0039\022AA5e+\005A\002CA\006\032\023\tQBBA\002J]RD\021\002\b\001A\002\003\007I\021A\017\002\r%$w\fJ3r)\tq\022\005\005\002\f?%\021\001\005\004\002\005+:LG\017C\004#7\005\005\t\031\001\r\002\007a$\023\007\003\004%\001\001\006K\001G\001\004S\022\004\003b\002\024\001\001\004%\taJ\001\005]\006lW-F\001)!\tICF\004\002\fU%\0211\006D\001\007!J,G-\0324\n\0055r#AB*ue&twM\003\002,\031!9\001\007\001a\001\n\003\t\024\001\0038b[\026|F%Z9\025\005y\021\004b\002\0220\003\003\005\r\001\013\005\007i\001\001\013\025\002\025\002\0139\fW.\032\021\t\023Y\002\001\031!a\001\n\0039\022\001\002;za\026D\021\002\017\001A\002\003\007I\021A\035\002\021QL\b/Z0%KF$\"A\b\036\t\017\t:\024\021!a\0011!1A\b\001Q!\na\tQ\001^=qK\002B\021B\020\001A\002\003\007I\021A\f\002\017i|g.Z0jI\"I\001\t\001a\001\002\004%\t!Q\001\fu>tWmX5e?\022*\027\017\006\002\037\005\"9!ePA\001\002\004A\002B\002#\001A\003&\001$\001\005{_:,w,\0333!\021%1\005\0011AA\002\023\005q#A\004d_6\024w,\0333\t\023!\003\001\031!a\001\n\003I\025aC2p[\n|\026\016Z0%KF$\"A\b&\t\017\t:\025\021!a\0011!1A\n\001Q!\na\t\001bY8nE~KG\r\t\005\n\035\002\001\r\0211A\005\002\035\nA\001[8ti\"I\001\013\001a\001\002\004%\t!U\001\tQ>\034Ho\030\023fcR\021aD\025\005\bE=\013\t\0211\001)\021\031!\006\001)Q\005Q\005)\001n\\:uA!Ia\013\001a\001\002\004%\taJ\001\003SBD\021\002\027\001A\002\003\007I\021A-\002\r%\004x\fJ3r)\tq\"\fC\004#/\006\005\t\031\001\025\t\rq\003\001\025)\003)\003\rI\007\017\t\005\b=\002\001\r\021\"\001\030\003\021\001xN\035;\t\017\001\004\001\031!C\001C\006A\001o\034:u?\022*\027\017\006\002\037E\"9!eXA\001\002\004A\002B\0023\001A\003&\001$A\003q_J$\b\005C\004g\001\001\007I\021A\f\002\rM$\030\r^;t\021\035A\007\0011A\005\002%\f!b\035;biV\034x\fJ3r)\tq\"\016C\004#O\006\005\t\031\001\r\t\r1\004\001\025)\003\031\003\035\031H/\031;vg\002BqA\034\001A\002\023\005q#\001\003jG>t\007b\0029\001\001\004%\t!]\001\tS\016|gn\030\023fcR\021aD\035\005\bE=\f\t\0211\001\031\021\031!\b\001)Q\0051\005)\021nY8oA!9a\017\001a\001\n\0039\022\001\0025jI\026Dq\001\037\001A\002\023\005\0210\001\005iS\022,w\fJ3r)\tq\"\020C\004#o\006\005\t\031\001\r\t\rq\004\001\025)\003\031\003\025A\027\016Z3!\021\035q\b\0011A\005\002]\t1\001]1z\021%\t\t\001\001a\001\n\003\t\031!A\004qCf|F%Z9\025\007y\t)\001C\004#\006\005\t\031\001\r\t\017\005%\001\001)Q\0051\005!\001/Y=!\021!\ti\001\001a\001\n\0039\022\001C5q?^D\027\016^3\t\023\005E\001\0011A\005\002\005M\021\001D5q?^D\027\016^3`I\025\fHc\001\020\002\026!A!%a\004\002\002\003\007\001\004C\004\002\032\001\001\013\025\002\r\002\023%\004xl\0365ji\026\004\003\002CA\017\001\001\007I\021A\f\002\027\r\024X-\031;f?J|G.\032\005\n\003C\001\001\031!C\001\003G\tqb\031:fCR,wL]8mK~#S-\035\013\004=\005\025\002\002\003\022\002 \005\005\t\031\001\r\t\017\005%\002\001)Q\0051\005a1M]3bi\026|&o\0347fA!A\021Q\006\001A\002\023\005q#A\005nCb|Fn\\4j]\"I\021\021\007\001A\002\023\005\0211G\001\016[\006Dx\f\\8hS:|F%Z9\025\007y\t)\004\003\005#\003_\t\t\0211\001\031\021\035\tI\004\001Q!\na\t!\"\\1y?2|w-\0338!\021!\ti\004\001a\001\n\0039\022\001D:fG>tGm\0307pO&t\007\"CA!\001\001\007I\021AA\"\003A\031XmY8oI~cwnZ5o?\022*\027\017F\002\037\003\013B\001BIA \003\003\005\r\001\007\005\b\003\023\002\001\025)\003\031\0035\031XmY8oI~cwnZ5oA!A\021Q\n\001A\002\023\005q#A\006xC&$xl]3d_:$\007\"CA)\001\001\007I\021AA*\003=9\030-\033;`g\026\034wN\0343`I\025\fHc\001\020\002V!A!%a\024\002\002\003\007\001\004C\004\002Z\001\001\013\025\002\r\002\031]\f\027\016^0tK\016|g\016\032\021\t\021\005u\003\0011A\005\002\035\nAb\0317pg\026|\006O]8naRD\021\"!\031\001\001\004%\t!a\031\002!\rdwn]3`aJ|W\016\035;`I\025\fHc\001\020\002f!A!%a\030\002\002\003\007\001\006C\004\002j\001\001\013\025\002\025\002\033\rdwn]3`aJ|W\016\035;!\021-\ti\007\001a\001\002\004%\t!a\034\002\023=\004XM\\0uS6,WCAA9!\021\t\031(! \016\005\005U$\002BA<\003s\nA!\036;jY*\021\0211P\001\005U\0064\030-\003\003\002\000\005U$\001\002#bi\026D1\"a!\001\001\004\005\r\021\"\001\002\006\006iq\016]3o?RLW.Z0%KF$2AHAD\021%\021\023\021QA\001\002\004\t\t\b\003\005\002\f\002\001\013\025BA9\003)y\007/\0328`i&lW\r\t\005\t\003\037\003\001\031!C\001/\005YQn\0348fs~c\027.\\5u\021%\t\031\n\001a\001\n\003\t)*A\bn_:,\027p\0307j[&$x\fJ3r)\rq\022q\023\005\tE\005E\025\021!a\0011!9\0211\024\001!B\023A\022\001D7p]\026Lx\f\\5nSR\004\003\002CAP\001\001\007I\021A\f\002\025\035|G\016Z0mS6LG\017C\005\002$\002\001\r\021\"\001\002&\006qqm\0347e?2LW.\033;`I\025\fHc\001\020\002(\"A!%!)\002\002\003\007\001\004C\004\002,\002\001\013\025\002\r\002\027\035|G\016Z0mS6LG\017\t\005\t\003_\003\001\031!C\001/\005y!-\0338e?\036|G\016Z0mS6LG\017C\005\0024\002\001\r\021\"\001\0026\006\031\"-\0338e?\036|G\016Z0mS6LGo\030\023fcR\031a$a.\t\021\t\n\t,!AA\002aAq!a/\001A\003&\001$\001\tcS:$wlZ8mI~c\027.\\5uA!A\021q\030\001A\002\023\005q#A\005fqB|F.[7ji\"I\0211\031\001A\002\023\005\021QY\001\016Kb\004x\f\\5nSR|F%Z9\025\007y\t9\r\003\005#\003\003\f\t\0211\001\031\021\035\tY\r\001Q!\na\t!\"\032=q?2LW.\033;!\021!\ty\r\001a\001\n\0039\022A\0035veR|F.[7ji\"I\0211\033\001A\002\023\005\021Q[\001\017QV\024Ho\0307j[&$x\fJ3r)\rq\022q\033\005\tE\005E\027\021!a\0011!9\0211\034\001!B\023A\022a\0035veR|F.[7ji\002B\001\"a8\001\001\004%\taF\001\016[>tW-_0mS6LGo\030;\t\023\005\r\b\0011A\005\002\005\025\030!E7p]\026Lx\f\\5nSR|Fo\030\023fcR\031a$a:\t\021\t\n\t/!AA\002aAq!a;\001A\003&\001$\001\bn_:,\027p\0307j[&$x\f\036\021\t\021\005=\b\0011A\005\002]\tAbZ8mI~c\027.\\5u?RD\021\"a=\001\001\004%\t!!>\002!\035|G\016Z0mS6LGo\030;`I\025\fHc\001\020\002x\"A!%!=\002\002\003\007\001\004C\004\002|\002\001\013\025\002\r\002\033\035|G\016Z0mS6LGo\030;!\021!\ty\020\001a\001\n\0039\022!\0052j]\022|vm\0347e?2LW.\033;`i\"I!1\001\001A\002\023\005!QA\001\026E&tGmX4pY\022|F.[7ji~#x\fJ3r)\rq\"q\001\005\tE\t\005\021\021!a\0011!9!1\002\001!B\023A\022A\0052j]\022|vm\0347e?2LW.\033;`i\002B\001Ba\004\001\001\004%\taF\001\fKb\004x\f\\5nSR|F\017C\005\003\024\001\001\r\021\"\001\003\026\005yQ\r\0379`Y&l\027\016^0u?\022*\027\017F\002\037\005/A\001B\tB\t\003\003\005\r\001\007\005\b\0057\001\001\025)\003\031\0031)\007\020]0mS6LGo\030;!\021!\021y\002\001a\001\n\0039\022\001\0045veR|F.[7ji~#\b\"\003B\022\001\001\007I\021\001B\023\003AAWO\035;`Y&l\027\016^0u?\022*\027\017F\002\037\005OA\001B\tB\021\003\003\005\r\001\007\005\b\005W\001\001\025)\003\031\0035AWO\035;`Y&l\027\016^0uA!I!q\006\001A\002\023\005!\021G\001\013o\006\024hnX3nC&dWC\001B\032!\021\021)Da\017\016\005\t]\"\002\002B\035\003s\nA\001\\1oO&\031QFa\016\t\023\t}\002\0011A\005\002\t\005\023AD<be:|V-\\1jY~#S-\035\013\004=\t\r\003\"\003\022\003>\005\005\t\031\001B\032\021!\0219\005\001Q!\n\tM\022aC<be:|V-\\1jY\002B\021Ba\023\001\001\004%\tA!\r\002\025\025l\027-\0337`CV$\b\016C\005\003P\001\001\r\021\"\001\003R\005qQ-\\1jY~\013W\017\0365`I\025\fHc\001\020\003T!I!E!\024\002\002\003\007!1\007\005\t\005/\002\001\025)\003\0034\005YQ-\\1jY~\013W\017\0365!\021%\021Y\006\001a\001\n\003\021i&\001\005sK\016|V.Y5m+\t\021y\006E\003\003b\t-\004&\004\002\003d)!!Q\rB4\003%IW.\\;uC\ndWMC\002\003j1\t!bY8mY\026\034G/[8o\023\021\021iGa\031\003\t1K7\017\036\005\n\005c\002\001\031!C\001\005g\nAB]3d?6\f\027\016\\0%KF$2A\bB;\021%\021#qNA\001\002\004\021y\006\003\005\003z\001\001\013\025\002B0\003%\021XmY0nC&d\007\005C\005\003~\001\001\r\021\"\001\0032\005QQ-\\1jY~Cwn\035;\t\023\t\005\005\0011A\005\002\t\r\025AD3nC&dw\f[8ti~#S-\035\013\004=\t\025\005\"\003\022\003\000\005\005\t\031\001B\032\021!\021I\t\001Q!\n\tM\022aC3nC&dw\f[8ti\002B\021B!$\001\001\004%\tA!\r\002\035\025l\027-\0337`aJ|Go\\2pY\"I!\021\023\001A\002\023\005!1S\001\023K6\f\027\016\\0qe>$xnY8m?\022*\027\017F\002\037\005+C\021B\tBH\003\003\005\rAa\r\t\021\te\005\001)Q\005\005g\tq\"Z7bS2|\006O]8u_\016|G\016\t\005\t\005;\003\001\031!C\001/\005QQ-\\1jY~\003xN\035;\t\023\t\005\006\0011A\005\002\t\r\026AD3nC&dw\f]8si~#S-\035\013\004=\t\025\006\002\003\022\003 \006\005\t\031\001\r\t\017\t%\006\001)Q\0051\005YQ-\\1jY~\003xN\035;!\021\035\021i\013\001C\001\005_\013A!\0338jiR\031aD!-\t\021\tM&1\026a\001\005k\013!b]3sm\026\024()Z1o!\021\0219L!0\016\005\te&b\001B^\t\005!1m\034:f\023\021\021yL!/\003\0175\013\007OQ3b]\"9!1\031\001\005\002\t\025\027\001D:fi^\013'O\034'j[&$Hc\001\020\003H\"A!\021\032Ba\001\004\021),\001\005xCJt')Z1o\021\035\021i\r\001C\001\005\037\f1bR3u\037B,g\016V5nKR\021\021\021\017\005\b\005'\004A\021\001Bk\003E9W\r^*feZ,'o\0249f]\022\013\027p\035\013\0021!9!\021\034\001\005\002\tm\027!D4fiNKW\016\0357f\023:4w.\006\002\0036\"9!q\034\001\005\002\t\005\030\001E5t'\026tGmU3sm\026\024X*Y5m+\t\021\031\017E\002\f\005KL1Aa:\r\005\035\021un\0347fC:\004")
/*     */ public class ServerDef {
/*  10 */   public int id() { return this.id; } private int id; public void id_$eq(int x$1) { this.id = x$1; }
/*  11 */    private String name = ""; private int type; private int zone_id; private int comb_id; private String host; private String ip; public String name() { return this.name; } public void name_$eq(String x$1) { this.name = x$1; }
/*     */   
/*  13 */   public int type() { return this.type; } public void type_$eq(int x$1) { this.type = x$1; }
/*  14 */   public int zone_id() { return this.zone_id; } public void zone_id_$eq(int x$1) { this.zone_id = x$1; }
/*  15 */   public int comb_id() { return this.comb_id; } public void comb_id_$eq(int x$1) { this.comb_id = x$1; }
/*  16 */   public String host() { return this.host; } public void host_$eq(String x$1) { this.host = x$1; }
/*  17 */   public String ip() { return this.ip; } public void ip_$eq(String x$1) { this.ip = x$1; }
/*  18 */    private int port = 8100; public int port() { return this.port; } public void port_$eq(int x$1) { this.port = x$1; }
/*     */   
/*  20 */   private int status = 3; public int status() { return this.status; } public void status_$eq(int x$1) { this.status = x$1; }
/*     */   
/*  22 */   private int icon = 0; public int icon() { return this.icon; } public void icon_$eq(int x$1) { this.icon = x$1; }
/*     */   
/*  24 */   private int hide = 0; public int hide() { return this.hide; } public void hide_$eq(int x$1) { this.hide = x$1; }
/*     */   
/*  26 */   private int pay = 1; public int pay() { return this.pay; } public void pay_$eq(int x$1) { this.pay = x$1; }
/*     */   
/*  28 */   private int ip_white = 0; public int ip_white() { return this.ip_white; } public void ip_white_$eq(int x$1) { this.ip_white = x$1; }
/*     */   
/*  30 */   private int create_role = 1; public int create_role() { return this.create_role; } public void create_role_$eq(int x$1) { this.create_role = x$1; }
/*     */   
/*  32 */   private int max_login = 3000; public int max_login() { return this.max_login; } public void max_login_$eq(int x$1) { this.max_login = x$1; }
/*     */   
/*  34 */   private int second_login = 0; public int second_login() { return this.second_login; } public void second_login_$eq(int x$1) { this.second_login = x$1; }
/*     */   
/*  36 */   private int wait_second = 1; public int wait_second() { return this.wait_second; } public void wait_second_$eq(int x$1) { this.wait_second = x$1; }
/*     */   
/*  38 */   private String close_prompt = "服务器维护中"; private Date open_time; public String close_prompt() { return this.close_prompt; } public void close_prompt_$eq(String x$1) { this.close_prompt = x$1; }
/*     */   
/*  40 */   public Date open_time() { return this.open_time; } public void open_time_$eq(Date x$1) { this.open_time = x$1; }
/*     */   
/*  42 */   private int money_limit = 0; public int money_limit() { return this.money_limit; } public void money_limit_$eq(int x$1) { this.money_limit = x$1; }
/*     */   
/*  44 */   private int gold_limit = 0; public int gold_limit() { return this.gold_limit; } public void gold_limit_$eq(int x$1) { this.gold_limit = x$1; }
/*     */   
/*  46 */   private int bind_gold_limit = 0; public int bind_gold_limit() { return this.bind_gold_limit; } public void bind_gold_limit_$eq(int x$1) { this.bind_gold_limit = x$1; }
/*     */   
/*  48 */   private int exp_limit = 0; public int exp_limit() { return this.exp_limit; } public void exp_limit_$eq(int x$1) { this.exp_limit = x$1; }
/*     */   
/*  50 */   private int hurt_limit = 0; public int hurt_limit() { return this.hurt_limit; } public void hurt_limit_$eq(int x$1) { this.hurt_limit = x$1; }
/*     */   
/*  52 */   private int money_limit_t = 0; public int money_limit_t() { return this.money_limit_t; } public void money_limit_t_$eq(int x$1) { this.money_limit_t = x$1; }
/*     */   
/*  54 */   private int gold_limit_t = 0; public int gold_limit_t() { return this.gold_limit_t; } public void gold_limit_t_$eq(int x$1) { this.gold_limit_t = x$1; }
/*     */   
/*  56 */   private int bind_gold_limit_t = 0; public int bind_gold_limit_t() { return this.bind_gold_limit_t; } public void bind_gold_limit_t_$eq(int x$1) { this.bind_gold_limit_t = x$1; }
/*     */   
/*  58 */   private int exp_limit_t = 0; public int exp_limit_t() { return this.exp_limit_t; } public void exp_limit_t_$eq(int x$1) { this.exp_limit_t = x$1; }
/*     */   
/*  60 */   private int hurt_limit_t = 0; public int hurt_limit_t() { return this.hurt_limit_t; } public void hurt_limit_t_$eq(int x$1) { this.hurt_limit_t = x$1; }
/*     */   
/*  62 */   private String warn_email = ""; public String warn_email() { return this.warn_email; } public void warn_email_$eq(String x$1) { this.warn_email = x$1; }
/*     */   
/*  64 */   private String email_auth = ""; public String email_auth() { return this.email_auth; } public void email_auth_$eq(String x$1) { this.email_auth = x$1; }
/*     */   
/*  66 */   private List<String> rec_mail = List$.MODULE$.empty(); public List<String> rec_mail() { return this.rec_mail; } public void rec_mail_$eq(List<String> x$1) { this.rec_mail = x$1; }
/*     */   
/*  68 */   private String email_host = ""; public String email_host() { return this.email_host; } public void email_host_$eq(String x$1) { this.email_host = x$1; }
/*     */   
/*  70 */   private String email_protocol = ""; public String email_protocol() { return this.email_protocol; } public void email_protocol_$eq(String x$1) { this.email_protocol = x$1; }
/*     */   
/*  72 */   private int email_port = 0; public int email_port() { return this.email_port; } public void email_port_$eq(int x$1) { this.email_port = x$1; }
/*     */    public void init(MapBean serverBean) {
/*     */     Date date;
/*  75 */     id_$eq(serverBean.getInt("id"));
/*  76 */     name_$eq(serverBean.getString("name"));
/*  77 */     type_$eq(serverBean.getInt("type"));
/*  78 */     zone_id_$eq(serverBean.getInt("zone_id"));
/*  79 */     comb_id_$eq(serverBean.getInt("comb_id"));
/*  80 */     host_$eq(serverBean.getString("host"));
/*  81 */     ip_$eq(serverBean.getString("ip"));
/*  82 */     port_$eq(serverBean.getInt("port"));
/*  83 */     status_$eq(serverBean.getInt("status"));
/*  84 */     icon_$eq(serverBean.getInt("icon"));
/*  85 */     hide_$eq(serverBean.getInt("hide"));
/*  86 */     pay_$eq(serverBean.getInt("pay"));
/*  87 */     ip_white_$eq(serverBean.getInt("ip_white"));
/*  88 */     create_role_$eq(serverBean.getInt("create_role"));
/*  89 */     max_login_$eq(serverBean.getInt("max_login"));
/*  90 */     second_login_$eq(serverBean.getInt("second_login"));
/*  91 */     wait_second_$eq(serverBean.getInt("wait_second"));
/*  92 */     close_prompt_$eq(serverBean.getString("close_prompt"));
/*     */     
/*  94 */     Object object = serverBean.apply("open_time");
/*  95 */     if (object instanceof Long) { date = new Date(serverBean.getLong("open_time")); }
/*  96 */     else { date = serverBean.getUtilDate("open_time"); }
/*     */     
/*     */     open_time_$eq(date);
/*     */   }
/*     */ 
/*     */   
/*     */   public void setWarnLimit(MapBean warnBean) {
/* 103 */     money_limit_$eq(warnBean.getInt("money"));
/* 104 */     gold_limit_$eq(warnBean.getInt("gold"));
/* 105 */     bind_gold_limit_$eq(warnBean.getInt("bind_gold"));
/* 106 */     exp_limit_$eq(warnBean.getInt("exp"));
/* 107 */     hurt_limit_$eq(warnBean.getInt("hurt"));
/* 108 */     warn_email_$eq(warnBean.getString("email"));
/* 109 */     email_auth_$eq(warnBean.getString("auth"));
/* 110 */     String tmp = warnBean.getString("rec_mail");
/* 111 */     if (tmp != null && tmp.length() > 0) rec_mail_$eq(Predef$.MODULE$.refArrayOps((Object[])tmp.split(",")).toList());
/*     */     
/* 113 */     money_limit_t_$eq(warnBean.getInt("money_t"));
/* 114 */     gold_limit_t_$eq(warnBean.getInt("gold_t"));
/* 115 */     bind_gold_limit_t_$eq(warnBean.getInt("bind_gold_t"));
/* 116 */     exp_limit_t_$eq(warnBean.getInt("exp_t"));
/* 117 */     hurt_limit_t_$eq(warnBean.getInt("hurt_t"));
/* 118 */     email_host_$eq(warnBean.getString("host"));
/* 119 */     email_protocol_$eq(warnBean.getString("protocol"));
/* 120 */     email_port_$eq(warnBean.getInt("port"));
/*     */   }
/*     */ 
/*     */   
/*     */   public Date GetOpenTime() {
/* 125 */     if (open_time() == null) {
/* 126 */       open_time_$eq(new Date());
/*     */     }
/* 128 */     return open_time();
/*     */   }
/*     */ 
/*     */ 
/*     */   
/*     */   public int getServerOpenDays() {
/* 134 */     return Tool$.MODULE$.differentDays(open_time(), new Date()) + 1;
/*     */   }
/*     */   
/*     */   public MapBean getSimpleInfo() {
/* 138 */     (new scala.Tuple2[6])[0] = Predef$ArrowAssoc$.MODULE$.$minus$greater$extension(Predef$.MODULE$.ArrowAssoc("id"), BoxesRunTime.boxToInteger(id())); (new scala.Tuple2[6])[1] = Predef$ArrowAssoc$.MODULE$.$minus$greater$extension(Predef$.MODULE$.ArrowAssoc("name"), name()); (new scala.Tuple2[6])[2] = Predef$ArrowAssoc$.MODULE$.$minus$greater$extension(Predef$.MODULE$.ArrowAssoc("host"), host()); (new scala.Tuple2[6])[3] = Predef$ArrowAssoc$.MODULE$.$minus$greater$extension(Predef$.MODULE$.ArrowAssoc("port"), BoxesRunTime.boxToInteger(port())); (new scala.Tuple2[6])[4] = Predef$ArrowAssoc$.MODULE$.$minus$greater$extension(Predef$.MODULE$.ArrowAssoc("status"), BoxesRunTime.boxToInteger(status())); (new scala.Tuple2[6])[5] = Predef$ArrowAssoc$.MODULE$.$minus$greater$extension(Predef$.MODULE$.ArrowAssoc("icon"), BoxesRunTime.boxToInteger(icon())); return MapBean$.MODULE$.apply((Seq)Predef$.MODULE$.wrapRefArray((Object[])new scala.Tuple2[6]));
/*     */   }
/*     */   
/*     */   public boolean isSendServerMail() {
/*     */     // Byte code:
/*     */     //   0: aload_0
/*     */     //   1: invokevirtual warn_email : ()Ljava/lang/String;
/*     */     //   4: ldc_w ''
/*     */     //   7: astore_1
/*     */     //   8: dup
/*     */     //   9: ifnonnull -> 20
/*     */     //   12: pop
/*     */     //   13: aload_1
/*     */     //   14: ifnull -> 133
/*     */     //   17: goto -> 27
/*     */     //   20: aload_1
/*     */     //   21: invokevirtual equals : (Ljava/lang/Object;)Z
/*     */     //   24: ifne -> 133
/*     */     //   27: aload_0
/*     */     //   28: invokevirtual email_auth : ()Ljava/lang/String;
/*     */     //   31: ldc_w ''
/*     */     //   34: astore_2
/*     */     //   35: dup
/*     */     //   36: ifnonnull -> 47
/*     */     //   39: pop
/*     */     //   40: aload_2
/*     */     //   41: ifnull -> 133
/*     */     //   44: goto -> 54
/*     */     //   47: aload_2
/*     */     //   48: invokevirtual equals : (Ljava/lang/Object;)Z
/*     */     //   51: ifne -> 133
/*     */     //   54: aload_0
/*     */     //   55: invokevirtual rec_mail : ()Lscala/collection/immutable/List;
/*     */     //   58: invokevirtual isEmpty : ()Z
/*     */     //   61: ifne -> 133
/*     */     //   64: aload_0
/*     */     //   65: invokevirtual email_host : ()Ljava/lang/String;
/*     */     //   68: ldc_w ''
/*     */     //   71: astore_3
/*     */     //   72: dup
/*     */     //   73: ifnonnull -> 84
/*     */     //   76: pop
/*     */     //   77: aload_3
/*     */     //   78: ifnull -> 133
/*     */     //   81: goto -> 91
/*     */     //   84: aload_3
/*     */     //   85: invokevirtual equals : (Ljava/lang/Object;)Z
/*     */     //   88: ifne -> 133
/*     */     //   91: aload_0
/*     */     //   92: invokevirtual email_protocol : ()Ljava/lang/String;
/*     */     //   95: ldc_w ''
/*     */     //   98: astore #4
/*     */     //   100: dup
/*     */     //   101: ifnonnull -> 113
/*     */     //   104: pop
/*     */     //   105: aload #4
/*     */     //   107: ifnull -> 133
/*     */     //   110: goto -> 121
/*     */     //   113: aload #4
/*     */     //   115: invokevirtual equals : (Ljava/lang/Object;)Z
/*     */     //   118: ifne -> 133
/*     */     //   121: aload_0
/*     */     //   122: invokevirtual email_port : ()I
/*     */     //   125: iconst_0
/*     */     //   126: if_icmpeq -> 133
/*     */     //   129: iconst_1
/*     */     //   130: goto -> 134
/*     */     //   133: iconst_0
/*     */     //   134: ireturn
/*     */     // Line number table:
/*     */     //   Java source line number -> byte code offset
/*     */     //   #141	-> 0
/*     */     // Local variable table:
/*     */     //   start	length	slot	name	descriptor
/*     */     //   0	135	0	this	Lcom/nirvana/bean/ServerDef;
/*     */   }
/*     */ }


/* Location:              D:\MTJ\mtj_master_jar\mtj_master.jar!\com\nirvana\bean\ServerDef.class
 * Java compiler version: 6 (50.0)
 * JD-Core Version:       1.1.3
 */