/*     */ package com.nirvana.holder;
/*     */ 
/*     */ import com.nirvana.bean.ServerDef;
/*     */ import com.nirvana.core.MapBean;
/*     */ import scala.Enumeration;
/*     */ import scala.Predef$;
/*     */ import scala.Predef$ArrowAssoc$;
/*     */ import scala.Serializable;
/*     */ import scala.collection.mutable.ListBuffer;
/*     */ import scala.collection.mutable.ListBuffer$;
/*     */ import scala.reflect.ScalaSignature;
/*     */ import scala.runtime.AbstractFunction1;
/*     */ import scala.runtime.BoxesRunTime;
/*     */ 
/*     */ 
/*     */ 
/*     */ 
/*     */ 
/*     */ 
/*     */ 
/*     */ 
/*     */ 
/*     */ 
/*     */ 
/*     */ 
/*     */ 
/*     */ 
/*     */ 
/*     */ 
/*     */ 
/*     */ 
/*     */ 
/*     */ 
/*     */ 
/*     */ 
/*     */ 
/*     */ 
/*     */ 
/*     */ 
/*     */ 
/*     */ 
/*     */ 
/*     */ 
/*     */ 
/*     */ 
/*     */ 
/*     */ 
/*     */ 
/*     */ 
/*     */ 
/*     */ 
/*     */ 
/*     */ 
/*     */ 
/*     */ 
/*     */ 
/*     */ 
/*     */ 
/*     */ 
/*     */ 
/*     */ 
/*     */ 
/*     */ 
/*     */ 
/*     */ 
/*     */ 
/*     */ 
/*     */ 
/*     */ 
/*     */ 
/*     */ 
/*     */ 
/*     */ 
/*     */ 
/*     */ 
/*     */ 
/*     */ 
/*     */ 
/*     */ 
/*     */ 
/*     */ 
/*     */ 
/*     */ 
/*     */ 
/*     */ 
/*     */ 
/*     */ 
/*     */ 
/*     */ 
/*     */ 
/*     */ 
/*     */ 
/*     */ 
/*     */ 
/*     */ 
/*     */ 
/*     */ 
/*     */ 
/*     */ 
/*     */ @ScalaSignature(bytes = "\006\001)4A!\001\002\001\023\t9!l\0348f\t\0264'BA\002\005\003\031Aw\016\0343fe*\021QAB\001\b]&\024h/\0318b\025\0059\021aA2p[\016\0011C\001\001\013!\tYa\"D\001\r\025\005i\021!B:dC2\f\027BA\b\r\005\031\te.\037*fM\")\021\003\001C\001%\0051A(\0338jiz\"\022a\005\t\003)\001i\021A\001\005\n-\001\001\r\0211A\005\002]\t!!\0333\026\003a\001\"aC\r\n\005ia!aA%oi\"IA\004\001a\001\002\004%\t!H\001\007S\022|F%Z9\025\005y\t\003CA\006 \023\t\001CB\001\003V]&$\bb\002\022\034\003\003\005\r\001G\001\004q\022\n\004B\002\023\001A\003&\001$A\002jI\002B\021B\n\001A\002\003\007I\021A\024\002\t9\fW.Z\013\002QA\021\021\006\f\b\003\027)J!a\013\007\002\rA\023X\rZ3g\023\ticF\001\004TiJLgn\032\006\003W1A\021\002\r\001A\002\003\007I\021A\031\002\0219\fW.Z0%KF$\"A\b\032\t\017\tz\023\021!a\001Q!1A\007\001Q!\n!\nQA\\1nK\002BqA\016\001C\002\023\005q'\001\006tKJ4XM\035'jgR,\022\001\017\t\004sy\002U\"\001\036\013\005mb\024aB7vi\006\024G.\032\006\003{1\t!bY8mY\026\034G/[8o\023\ty$H\001\006MSN$()\0364gKJ\004\"!\021#\016\003\tS!a\021\003\002\t\t,\027M\\\005\003\013\n\023\021bU3sm\026\024H)\0324\t\r\035\003\001\025!\0039\003-\031XM\035<fe2K7\017\036\021\t\013%\003A\021\001&\002\017\035,G/\0238g_R)1*\0250aEB\021AjT\007\002\033*\021a\nB\001\005G>\024X-\003\002Q\033\n9Q*\0319CK\006t\007\"\002*I\001\004\031\026\001\0049mCR4wN]7UsB,\007C\001+[\035\t)\006,D\001W\025\t9F!\001\005qY\006$hm\034:n\023\tIf+\001\tVg\026\024\b\013\\1uM>\024X\016V=qK&\0211\f\030\002\006-\006dW/Z\005\003;2\0211\"\0228v[\026\024\030\r^5p]\")q\f\023a\0011\005I1\r[1o]\026d\027\n\032\005\006C\"\003\r\001K\001\004m\026\024\b\"B2I\001\004A\023AA5q\021\025)\007\001\"\001g\00359W\r^*feZ,'/\0238g_R\0311jZ5\t\013!$\007\031\001!\002\023M,'O^3s\t\0264\007\"B0e\001\004A\002")
/*     */ public class ZoneDef
/*     */ {
/*     */   private int id;
/*     */   private String name;
/*     */   
/*     */   public int id() {
/* 107 */     return this.id; } public void id_$eq(int x$1) { this.id = x$1; }
/* 108 */   public String name() { return this.name; } public void name_$eq(String x$1) { this.name = x$1; }
/* 109 */    private final ListBuffer<ServerDef> serverList = (ListBuffer<ServerDef>)ListBuffer$.MODULE$.empty(); public ListBuffer<ServerDef> serverList() { return this.serverList; }
/*     */    public MapBean getInfo(Enumeration.Value platformType, int channelId, String ver, String ip) {
/*     */     // Byte code:
/*     */     //   0: getstatic com/nirvana/holder/ServerHolder$.MODULE$ : Lcom/nirvana/holder/ServerHolder$;
/*     */     //   3: aload_3
/*     */     //   4: invokevirtual isApprovalVer : (Ljava/lang/String;)Z
/*     */     //   7: ifeq -> 31
/*     */     //   10: aload_0
/*     */     //   11: invokevirtual serverList : ()Lscala/collection/mutable/ListBuffer;
/*     */     //   14: new com/nirvana/holder/ZoneDef$$anonfun$4
/*     */     //   17: dup
/*     */     //   18: aload_0
/*     */     //   19: invokespecial <init> : (Lcom/nirvana/holder/ZoneDef;)V
/*     */     //   22: invokevirtual filter : (Lscala/Function1;)Ljava/lang/Object;
/*     */     //   25: checkcast scala/collection/AbstractSeq
/*     */     //   28: goto -> 280
/*     */     //   31: aload_1
/*     */     //   32: astore #6
/*     */     //   34: getstatic com/nirvana/platform/UserPlatformType$.MODULE$ : Lcom/nirvana/platform/UserPlatformType$;
/*     */     //   37: invokevirtual DEFAULT : ()Lscala/Enumeration$Value;
/*     */     //   40: aload #6
/*     */     //   42: astore #7
/*     */     //   44: dup
/*     */     //   45: ifnonnull -> 57
/*     */     //   48: pop
/*     */     //   49: aload #7
/*     */     //   51: ifnull -> 65
/*     */     //   54: goto -> 90
/*     */     //   57: aload #7
/*     */     //   59: invokevirtual equals : (Ljava/lang/Object;)Z
/*     */     //   62: ifeq -> 90
/*     */     //   65: aload_0
/*     */     //   66: invokevirtual serverList : ()Lscala/collection/mutable/ListBuffer;
/*     */     //   69: new com/nirvana/holder/ZoneDef$$anonfun$5
/*     */     //   72: dup
/*     */     //   73: aload_0
/*     */     //   74: aload #4
/*     */     //   76: invokespecial <init> : (Lcom/nirvana/holder/ZoneDef;Ljava/lang/String;)V
/*     */     //   79: invokevirtual filter : (Lscala/Function1;)Ljava/lang/Object;
/*     */     //   82: checkcast scala/collection/AbstractSeq
/*     */     //   85: astore #8
/*     */     //   87: goto -> 278
/*     */     //   90: getstatic com/nirvana/platform/UserPlatformType$.MODULE$ : Lcom/nirvana/platform/UserPlatformType$;
/*     */     //   93: invokevirtual AOFEI : ()Lscala/Enumeration$Value;
/*     */     //   96: aload #6
/*     */     //   98: astore #9
/*     */     //   100: dup
/*     */     //   101: ifnonnull -> 113
/*     */     //   104: pop
/*     */     //   105: aload #9
/*     */     //   107: ifnull -> 121
/*     */     //   110: goto -> 150
/*     */     //   113: aload #9
/*     */     //   115: invokevirtual equals : (Ljava/lang/Object;)Z
/*     */     //   118: ifeq -> 150
/*     */     //   121: aload_0
/*     */     //   122: invokevirtual serverList : ()Lscala/collection/mutable/ListBuffer;
/*     */     //   125: new com/nirvana/holder/ZoneDef$$anonfun$6
/*     */     //   128: dup
/*     */     //   129: aload_0
/*     */     //   130: iload_2
/*     */     //   131: aload #4
/*     */     //   133: invokespecial <init> : (Lcom/nirvana/holder/ZoneDef;ILjava/lang/String;)V
/*     */     //   136: invokevirtual filter : (Lscala/Function1;)Ljava/lang/Object;
/*     */     //   139: checkcast scala/collection/mutable/ListBuffer
/*     */     //   142: invokevirtual toList : ()Lscala/collection/immutable/List;
/*     */     //   145: astore #8
/*     */     //   147: goto -> 278
/*     */     //   150: getstatic com/nirvana/platform/UserPlatformType$.MODULE$ : Lcom/nirvana/platform/UserPlatformType$;
/*     */     //   153: invokevirtual AOFEI_IOS : ()Lscala/Enumeration$Value;
/*     */     //   156: aload #6
/*     */     //   158: astore #10
/*     */     //   160: dup
/*     */     //   161: ifnonnull -> 173
/*     */     //   164: pop
/*     */     //   165: aload #10
/*     */     //   167: ifnull -> 181
/*     */     //   170: goto -> 210
/*     */     //   173: aload #10
/*     */     //   175: invokevirtual equals : (Ljava/lang/Object;)Z
/*     */     //   178: ifeq -> 210
/*     */     //   181: aload_0
/*     */     //   182: invokevirtual serverList : ()Lscala/collection/mutable/ListBuffer;
/*     */     //   185: new com/nirvana/holder/ZoneDef$$anonfun$7
/*     */     //   188: dup
/*     */     //   189: aload_0
/*     */     //   190: iload_2
/*     */     //   191: aload #4
/*     */     //   193: invokespecial <init> : (Lcom/nirvana/holder/ZoneDef;ILjava/lang/String;)V
/*     */     //   196: invokevirtual filter : (Lscala/Function1;)Ljava/lang/Object;
/*     */     //   199: checkcast scala/collection/mutable/ListBuffer
/*     */     //   202: invokevirtual toList : ()Lscala/collection/immutable/List;
/*     */     //   205: astore #8
/*     */     //   207: goto -> 278
/*     */     //   210: getstatic com/nirvana/platform/UserPlatformType$.MODULE$ : Lcom/nirvana/platform/UserPlatformType$;
/*     */     //   213: invokevirtual NOX : ()Lscala/Enumeration$Value;
/*     */     //   216: aload #6
/*     */     //   218: astore #11
/*     */     //   220: dup
/*     */     //   221: ifnonnull -> 233
/*     */     //   224: pop
/*     */     //   225: aload #11
/*     */     //   227: ifnull -> 241
/*     */     //   230: goto -> 270
/*     */     //   233: aload #11
/*     */     //   235: invokevirtual equals : (Ljava/lang/Object;)Z
/*     */     //   238: ifeq -> 270
/*     */     //   241: aload_0
/*     */     //   242: invokevirtual serverList : ()Lscala/collection/mutable/ListBuffer;
/*     */     //   245: new com/nirvana/holder/ZoneDef$$anonfun$8
/*     */     //   248: dup
/*     */     //   249: aload_0
/*     */     //   250: iload_2
/*     */     //   251: aload #4
/*     */     //   253: invokespecial <init> : (Lcom/nirvana/holder/ZoneDef;ILjava/lang/String;)V
/*     */     //   256: invokevirtual filter : (Lscala/Function1;)Ljava/lang/Object;
/*     */     //   259: checkcast scala/collection/mutable/ListBuffer
/*     */     //   262: invokevirtual toList : ()Lscala/collection/immutable/List;
/*     */     //   265: astore #8
/*     */     //   267: goto -> 278
/*     */     //   270: getstatic scala/collection/immutable/List$.MODULE$ : Lscala/collection/immutable/List$;
/*     */     //   273: invokevirtual empty : ()Lscala/collection/immutable/List;
/*     */     //   276: astore #8
/*     */     //   278: aload #8
/*     */     //   280: astore #5
/*     */     //   282: aload #5
/*     */     //   284: invokevirtual isEmpty : ()Z
/*     */     //   287: ifeq -> 294
/*     */     //   290: aconst_null
/*     */     //   291: goto -> 412
/*     */     //   294: getstatic com/nirvana/core/MapBean$.MODULE$ : Lcom/nirvana/core/MapBean$;
/*     */     //   297: getstatic scala/Predef$.MODULE$ : Lscala/Predef$;
/*     */     //   300: iconst_1
/*     */     //   301: anewarray scala/Tuple2
/*     */     //   304: dup
/*     */     //   305: iconst_0
/*     */     //   306: getstatic scala/Predef$ArrowAssoc$.MODULE$ : Lscala/Predef$ArrowAssoc$;
/*     */     //   309: getstatic scala/Predef$.MODULE$ : Lscala/Predef$;
/*     */     //   312: ldc 'id'
/*     */     //   314: invokevirtual ArrowAssoc : (Ljava/lang/Object;)Ljava/lang/Object;
/*     */     //   317: aload_0
/*     */     //   318: invokevirtual id : ()I
/*     */     //   321: invokestatic boxToInteger : (I)Ljava/lang/Integer;
/*     */     //   324: invokevirtual $minus$greater$extension : (Ljava/lang/Object;Ljava/lang/Object;)Lscala/Tuple2;
/*     */     //   327: aastore
/*     */     //   328: checkcast [Ljava/lang/Object;
/*     */     //   331: invokevirtual wrapRefArray : ([Ljava/lang/Object;)Lscala/collection/mutable/WrappedArray;
/*     */     //   334: invokevirtual apply : (Lscala/collection/Seq;)Lcom/nirvana/core/MapBean;
/*     */     //   337: astore #12
/*     */     //   339: aload #12
/*     */     //   341: getstatic scala/Predef$ArrowAssoc$.MODULE$ : Lscala/Predef$ArrowAssoc$;
/*     */     //   344: getstatic scala/Predef$.MODULE$ : Lscala/Predef$;
/*     */     //   347: ldc 'name'
/*     */     //   349: invokevirtual ArrowAssoc : (Ljava/lang/Object;)Ljava/lang/Object;
/*     */     //   352: getstatic com/nirvana/holder/ServerHolder$.MODULE$ : Lcom/nirvana/holder/ServerHolder$;
/*     */     //   355: aload_0
/*     */     //   356: invokevirtual id : ()I
/*     */     //   359: iload_2
/*     */     //   360: invokevirtual getChannelZoneName : (II)Ljava/lang/String;
/*     */     //   363: invokevirtual $minus$greater$extension : (Ljava/lang/Object;Ljava/lang/Object;)Lscala/Tuple2;
/*     */     //   366: invokevirtual $plus$eq : (Lscala/Tuple2;)Lscala/collection/mutable/HashMap;
/*     */     //   369: pop
/*     */     //   370: aload #12
/*     */     //   372: getstatic scala/Predef$ArrowAssoc$.MODULE$ : Lscala/Predef$ArrowAssoc$;
/*     */     //   375: getstatic scala/Predef$.MODULE$ : Lscala/Predef$;
/*     */     //   378: ldc 'l'
/*     */     //   380: invokevirtual ArrowAssoc : (Ljava/lang/Object;)Ljava/lang/Object;
/*     */     //   383: aload #5
/*     */     //   385: new com/nirvana/holder/ZoneDef$$anonfun$getInfo$1
/*     */     //   388: dup
/*     */     //   389: aload_0
/*     */     //   390: iload_2
/*     */     //   391: invokespecial <init> : (Lcom/nirvana/holder/ZoneDef;I)V
/*     */     //   394: getstatic scala/collection/Seq$.MODULE$ : Lscala/collection/Seq$;
/*     */     //   397: invokevirtual canBuildFrom : ()Lscala/collection/generic/CanBuildFrom;
/*     */     //   400: invokevirtual map : (Lscala/Function1;Lscala/collection/generic/CanBuildFrom;)Ljava/lang/Object;
/*     */     //   403: invokevirtual $minus$greater$extension : (Ljava/lang/Object;Ljava/lang/Object;)Lscala/Tuple2;
/*     */     //   406: invokevirtual $plus$eq : (Lscala/Tuple2;)Lscala/collection/mutable/HashMap;
/*     */     //   409: pop
/*     */     //   410: aload #12
/*     */     //   412: areturn
/*     */     // Line number table:
/*     */     //   Java source line number -> byte code offset
/*     */     //   #113	-> 0
/*     */     //   #114	-> 10
/*     */     //   #116	-> 31
/*     */     //   #117	-> 34
/*     */     //   #118	-> 65
/*     */     //   #119	-> 90
/*     */     //   #120	-> 121
/*     */     //   #121	-> 142
/*     */     //   #122	-> 150
/*     */     //   #123	-> 181
/*     */     //   #124	-> 202
/*     */     //   #125	-> 210
/*     */     //   #126	-> 241
/*     */     //   #127	-> 262
/*     */     //   #128	-> 270
/*     */     //   #116	-> 278
/*     */     //   #112	-> 280
/*     */     //   #132	-> 282
/*     */     //   #137	-> 290
/*     */     //   #133	-> 294
/*     */     //   #134	-> 339
/*     */     //   #135	-> 370
/*     */     //   #136	-> 410
/*     */     //   #111	-> 412
/*     */     // Local variable table:
/*     */     //   start	length	slot	name	descriptor
/*     */     //   0	413	0	this	Lcom/nirvana/holder/ZoneDef;
/*     */     //   0	413	1	platformType	Lscala/Enumeration$Value;
/*     */     //   0	413	2	channelId	I
/*     */     //   0	413	3	ver	Ljava/lang/String;
/*     */     //   0	413	4	ip	Ljava/lang/String;
/*     */     //   282	131	5	list	Lscala/collection/AbstractSeq;
/*     */     //   339	73	12	info	Lcom/nirvana/core/MapBean;
/*     */   } public final class ZoneDef$$anonfun$4 extends AbstractFunction1<ServerDef, Object> implements Serializable { public static final long serialVersionUID = 0L;
/*     */     public final boolean apply(ServerDef x$5) {
/* 114 */       return (x$5.type() == 1);
/*     */     } public ZoneDef$$anonfun$4(ZoneDef $outer) {} } public final class ZoneDef$$anonfun$5 extends AbstractFunction1<ServerDef, Object> implements Serializable { public static final long serialVersionUID = 0L; private final String ip$2;
/*     */     public ZoneDef$$anonfun$5(ZoneDef $outer, String ip$2) {}
/*     */     public final boolean apply(ServerDef server) {
/* 118 */       return (server.type() == 0 && (server.hide() == 0 || (server.hide() == 1 && ServerHolder$.MODULE$.ipCheck(server.id(), this.ip$2))));
/*     */     } } public final class ZoneDef$$anonfun$6 extends AbstractFunction1<ServerDef, Object> implements Serializable { public static final long serialVersionUID = 0L; private final int channelId$2; private final String ip$2; public final boolean apply(ServerDef server) {
/* 120 */       return (server.type() == 0 && ServerHolder$.MODULE$.isChannelServer(server.id(), this.channelId$2) && (
/* 121 */         server.hide() == 0 || (server.hide() == 1 && ServerHolder$.MODULE$.ipCheck(server.id(), this.ip$2))));
/*     */     } public ZoneDef$$anonfun$6(ZoneDef $outer, int channelId$2, String ip$2) {} } public final class ZoneDef$$anonfun$7 extends AbstractFunction1<ServerDef, Object> implements Serializable { public static final long serialVersionUID = 0L; private final int channelId$2; private final String ip$2; public final boolean apply(ServerDef server) {
/* 123 */       return (server.type() == 0 && ServerHolder$.MODULE$.isChannelServer(server.id(), this.channelId$2) && (
/* 124 */         server.hide() == 0 || (server.hide() == 1 && ServerHolder$.MODULE$.ipCheck(server.id(), this.ip$2))));
/*     */     } public ZoneDef$$anonfun$7(ZoneDef $outer, int channelId$2, String ip$2) {} } public final class ZoneDef$$anonfun$8 extends AbstractFunction1<ServerDef, Object> implements Serializable { public static final long serialVersionUID = 0L; private final int channelId$2; private final String ip$2; public final boolean apply(ServerDef server) {
/* 126 */       return (server.type() == 0 && ServerHolder$.MODULE$.isChannelServer(server.id(), this.channelId$2) && (
/* 127 */         server.hide() == 0 || (server.hide() == 1 && ServerHolder$.MODULE$.ipCheck(server.id(), this.ip$2))));
/*     */     }
/*     */     public ZoneDef$$anonfun$8(ZoneDef $outer, int channelId$2, String ip$2) {} }
/*     */   
/*     */   public final class ZoneDef$$anonfun$getInfo$1 extends AbstractFunction1<ServerDef, MapBean> implements Serializable { public static final long serialVersionUID = 0L;
/*     */     private final int channelId$2;
/*     */     
/*     */     public final MapBean apply(ServerDef x$6) {
/* 135 */       return this.$outer.getServerInfo(x$6, this.channelId$2);
/*     */     }
/*     */     
/*     */     public ZoneDef$$anonfun$getInfo$1(ZoneDef $outer, int channelId$2) {} }
/*     */   
/*     */   public MapBean getServerInfo(ServerDef serverDef, int channelId) {
/* 141 */     MapBean info = serverDef.getSimpleInfo();
/* 142 */     info.$plus$eq(Predef$ArrowAssoc$.MODULE$.$minus$greater$extension(Predef$.MODULE$.ArrowAssoc("name"), ServerHolder$.MODULE$.getChannelServerName(serverDef.id(), channelId)));
/* 143 */     return info;
/*     */   }
/*     */ }


/* Location:              D:\MTJ\mtj_master_jar\mtj_master.jar!\com\nirvana\holder\ZoneDef.class
 * Java compiler version: 6 (50.0)
 * JD-Core Version:       1.1.3
 */